Workbook

Sheet Leyenda
A1: DealCommerce · Diccionario de datos
A2: Versión 1 · 04-10-2026 · Pedro Santibáñez y Daniel Azócar · PostgreSQL 17 con Django
A4: Hojas
A5: Índice | B5: Una fila por tabla: grupo, estado, descripción y cantidad de campos.
A6: Diccionario | B6: Una fila por campo de cada tabla. Usa los filtros del encabezado para ver una tabla o un estado.
A7: Restricciones | B7: Reglas de unicidad y de validación que no caben en un solo campo.
A9: Estado de cada tabla
A10: Implementado | B10: Existe en el código (backend/apps).
A11: Planificado | B11: Diseñado, todavía sin programar. Puede cambiar al implementarse.
A12: Decisión pendiente | B12: Existe en el código, pero se decide con el cliente si se mantiene.
A13: Congelado | B13: Existe en el código, pero no se avanza hasta que el cliente lo confirme.
A15: Columna Clave
A16: PK | B16: Clave primaria.
A17: FK | B17: Clave foránea. La columna Referencia indica la tabla y qué pasa al borrar (CASCADE, PROTECT, SET NULL).
A18: UQ | B18: Valor único (solo o combinado con la tienda; ver Restricciones).
A20: Reglas generales
A21: Aislamiento | B21: Toda tabla con tienda_id pertenece a una tienda. Toda consulta se filtra por la tienda del usuario autenticado; pedir un dato de otra tienda responde 404.
A22: Montos | B22: Pesos chilenos enteros, netos (sin IVA). El IVA (19%) se calcula aparte con Decimal y redondeo medio hacia arriba.
A23: Gramos | B23: Decimal, nunca Float.
A24: Fechas | B24: Se guardan en UTC y se muestran en hora de Chile (America/Santiago).
A25: Archivos | B25: Las imágenes y planillas viven en Cloudflare R2; la base guarda solo la clave del objeto.
A26: Base común | B26: Las tablas con tienda heredan tienda_id, fecha_creacion y fecha_edicion del modelo base ModeloDeTienda.
A27: Django | B27: La tabla usuario además usa las tablas de grupos y permisos propias de Django, que no se detallan aquí.

Sheet Índice
A1: N° | B1: Tabla | C1: Modelo Django | D1: Grupo | E1: Estado | F1: Campos | G1: Descripción
A2: 1 | B2: tienda | C2: Tienda | D2: Identidad y acceso | E2: Implementado | F2: =COUNTIF(Diccionario!$A$2:$A$220,B2) -> 13 | G2: Cada comercio suscrito a la plataforma. Es la raíz del aislamiento: todo dato cuelga de una tienda.
A3: 2 | B3: usuario | C3: Usuario | D3: Identidad y acceso | E3: Implementado | F3: =COUNTIF(Diccionario!$A$2:$A$220,B3) -> 12 | G3: Cuentas de acceso. El rol define qué puede hacer; la tienda define qué datos puede ver.
A4: 3 | B4: solicitud_de_acceso | C4: SolicitudDeAcceso | D4: Identidad y acceso | E4: Implementado | F4: =COUNTIF(Diccionario!$A$2:$A$220,B4) -> 9 | G4: Negocios que pidieron entrar a la plataforma desde la portada. Única tabla sin tienda: existe antes de que la tienda exista.
A5: 4 | B5: aprobacion_mayorista | C5: AprobacionMayorista | D5: Identidad y acceso | E5: Decisión pendiente | F5: =COUNTIF(Diccionario!$A$2:$A$220,B5) -> 8 | G5: Estado de un comprador en una tienda. Pendiente de decidir si se mantiene, se adapta o se elimina, según si el cliente aprueba compradores.
A6: 5 | B6: categoria | C6: Categoria | D6: Catálogo y precios | E6: Planificado | F6: =COUNTIF(Diccionario!$A$2:$A$220,B6) -> 5 | G6: Categorías de pieza de cada tienda. Las usan la composición de los lotes y el pronóstico.
A7: 6 | B7: lote | C7: Lote | D7: Catálogo y precios | E7: Planificado | F7: =COUNTIF(Diccionario!$A$2:$A$220,B7) -> 14 | G7: Unidad de venta cerrada. Es una composición (piezas por categoría), no una lista de piezas concretas.
A8: 7 | B8: composicion_lote | C8: ComposicionLote | D8: Catálogo y precios | E8: Planificado | F8: =COUNTIF(Diccionario!$A$2:$A$220,B8) -> 7 | G8: Cuántas piezas de cada categoría trae un lote.
A9: 8 | B9: linea_granel | C9: LineaGranel | D9: Catálogo y precios | E9: Planificado | F9: =COUNTIF(Diccionario!$A$2:$A$220,B9) -> 10 | G9: Venta por gramo. No tiene stock: el dueño la activa o desactiva a mano.
A10: 9 | B10: tramo_precio | C10: TramoPrecio | D10: Catálogo y precios | E10: Planificado | F10: =COUNTIF(Diccionario!$A$2:$A$220,B10) -> 8 | G10: Tramos de precio por cantidad, para una línea de granel o para los lotes de la tienda.
A11: 10 | B11: pedido | C11: Pedido | D11: Pedidos | E11: Planificado | F11: =COUNTIF(Diccionario!$A$2:$A$220,B11) -> 12 | G11: Pedido de un comprador. Checkout simulado: no se cobra; el pago se coordina por WhatsApp.
A12: 11 | B12: linea_pedido | C12: LineaPedido | D12: Pedidos | E12: Planificado | F12: =COUNTIF(Diccionario!$A$2:$A$220,B12) -> 10 | G12: Cada lote o cantidad de gramos dentro de un pedido.
A13: 12 | B13: carga | C13: Carga | D13: Carga masiva | E13: Planificado | F13: =COUNTIF(Diccionario!$A$2:$A$220,B13) -> 12 | G13: Registro de cada planilla o .zip subido. Sirve para auditar de dónde salió cada dato del catálogo.
... A22: 21 | B22: envio_correo | C22: EnvioCorreo | D22: Agenda de visitas | E22: Congelado | F22: =COUNTIF(Diccionario!$A$2:$A$220,B22) -> 11 | G22: Correos de la agenda. Un fallo de envío no pierde la visita: se reintenta.
E23: Total campos | F23: =SUM(F2:F22) -> 219
D25: Tablas por estado | E25: Implementado | F25: =COUNTIF(E2:E22,E25) -> 3
E26: Planificado | F26: =COUNTIF(E2:E22,E26) -> 12
E27: Decisión pendiente | F27: =COUNTIF(E2:E22,E27) -> 1
E28: Congelado | F28: =COUNTIF(E2:E22,E28) -> 5

Sheet Diccionario
A1: Tabla | B1: Modelo Django | C1: Grupo | D1: Estado | E1: N° | F1: Campo | G1: Tipo PostgreSQL | H1: Tipo Django | I1: Nulo | J1: Clave | K1: Referencia · al borrar | L1: Valor por defecto | M1: Reglas y valores permitidos | N1: Descripción
A2: tienda | B2: Tienda | C2: Identidad y acceso | D2: Implementado | E2: 1 | F2: id | G2: bigint | H2: BigAutoField | I2: No | J2: PK | L2: Autoincremental | N2: Identificador interno.
A3: tienda | B3: Tienda | C3: Identidad y acceso | D3: Implementado | E3: 2 | F3: slug | G3: varchar(60) | H3: SlugField | I3: No | J3: UQ | M3: Único. Solo minúsculas, números y guiones. | N3: Identificador público; va en la ruta /t/<slug>/.
A4: tienda | B4: Tienda | C4: Identidad y acceso | D4: Implementado | E4: 3 | F4: nombre | G4: varchar(120) | H4: CharField | I4: No | N4: Nombre comercial de la tienda.
A5: tienda | B5: Tienda | C5: Identidad y acceso | D5: Implementado | E5: 4 | F5: activa | G5: boolean | H5: BooleanField | I5: No | L5: true | N5: Una tienda inactiva no se muestra al público.
A6: tienda | B6: Tienda | C6: Identidad y acceso | D6: Implementado | E6: 5 | F6: logo | G6: varchar(100) | H6: ImageField | I6: Sí | M6: Archivo en Cloudflare R2; se guarda solo la clave. | N6: Logo de la tienda.
A7: tienda | B7: Tienda | C7: Identidad y acceso | D7: Implementado | E7: 6 | F7: banner | G7: varchar(100) | H7: ImageField | I7: Sí | M7: Archivo en Cloudflare R2; se guarda solo la clave. | N7: Imagen de portada de la tienda.
A8: tienda | B8: Tienda | C8: Identidad y acceso | D8: Implementado | E8: 7 | F8: color_primario | G8: varchar(7) | H8: CharField | I8: Sí (vacío) | M8: Formato hexadecimal #RRGGBB, validado. Nunca CSS libre. | N8: Color principal de la tienda.
A9: tienda | B9: Tienda | C9: Identidad y acceso | D9: Implementado | E9: 8 | F9: color_primario_hover | G9: varchar(7) | H9: CharField | I9: Sí (vacío) | M9: Formato hexadecimal #RRGGBB, validado. | N9: Color principal al pasar el mouse.
A10: tienda | B10: Tienda | C10: Identidad y acceso | D10: Implementado | E10: 9 | F10: color_acento | G10: varchar(7) | H10: CharField | I10: Sí (vacío) | M10: Formato hexadecimal #RRGGBB, validado. | N10: Color de acento.
A11: tienda | B11: Tienda | C11: Identidad y acceso | D11: Implementado | E11: 10 | F11: color_destacado | G11: varchar(7) | H11: CharField | I11: Sí (vacío) | M11: Formato hexadecimal #RRGGBB, validado. | N11: Color para destacados.
A12: tienda | B12: Tienda | C12: Identidad y acceso | D12: Implementado | E12: 11 | F12: whatsapp | G12: varchar(200) | H12: URLField | I12: Sí (vacío) | M12: URL válida. | N12: Enlace de WhatsApp de la tienda.
A13: tienda | B13: Tienda | C13: Identidad y acceso | D13: Implementado | E13: 12 | F13: instagram | G13: varchar(200) | H13: URLField | I13: Sí (vacío) | M13: URL válida. | N13: Enlace de Instagram de la tienda.
A14: tienda | B14: Tienda | C14: Identidad y acceso | D14: Implementado | E14: 13 | F14: fecha_creacion | G14: timestamp with time zone | H14: DateTimeField(auto_now_add) | I14: No | L14: Ahora | N14: Fecha de alta de la tienda.
A15: usuario | B15: Usuario | C15: Identidad y acceso | D15: Implementado | E15: 1 | F15: id | G15: bigint | H15: BigAutoField | I15: No | J15: PK | L15: Autoincremental | N15: Identificador interno.
A16: usuario | B16: Usuario | C16: Identidad y acceso | D16: Implementado | E16: 2 | F16: email | G16: varchar(254) | H16: EmailField | I16: No | J16: UQ | M16: Se guarda en minúsculas. Es el nombre de usuario. | N16: Correo de la cuenta.
A17: usuario | B17: Usuario | C17: Identidad y acceso | D17: Implementado | E17: 3 | F17: password | G17: varchar(128) | H17: CharField (Django) | I17: No | M17: Hash; nunca la contraseña en texto plano. | N17: Contraseña cifrada.
A18: usuario | B18: Usuario | C18: Identidad y acceso | D18: Implementado | E18: 4 | F18: nombre | G18: varchar(150) | H18: CharField | I18: No | N18: Nombre de la persona.
A19: usuario | B19: Usuario | C19: Identidad y acceso | D19: Implementado | E19: 5 | F19: rut | G19: varchar(12) | H19: CharField | I19: Sí | J19: UQ | M19: Formato 12345678-5, sin puntos; dígito verificador validado. | N19: RUT chileno, opcional.
A20: usuario | B20: Usuario | C20: Identidad y acceso | D20: Implementado | E20: 6 | F20: rol | G20: varchar(20) | H20: CharField(choices) | I20: No | M20: admin_plataforma | dueno_tienda | vendedor | comprador | N20: Rol de la cuenta.
A21: usuario | B21: Usuario | C21: Identidad y acceso | D21: Implementado | E21: 7 | F21: tienda_id | G21: bigint | H21: ForeignKey(Tienda) | I21: Sí | J21: FK | K21: tienda.id · PROTECT | M21: CHECK: obligatorio para dueno_tienda y vendedor; nulo para admin_plataforma y comprador. | N21: Tienda donde trabaja la persona.
A22: usuario | B22: Usuario | C22: Identidad y acceso | D22: Implementado | E22: 8 | F22: is_active | G22: boolean | H22: BooleanField | I22: No | L22: true | N22: Cuenta habilitada.
A23: usuario | B23: Usuario | C23: Identidad y acceso | D23: Implementado | E23: 9 | F23: is_staff | G23: boolean | H23: BooleanField | I23: No | L23: false | N23: Puede entrar al panel de administración de Django.
A24: usuario | B24: Usuario | C24: Identidad y acceso | D24: Implementado | E24: 10 | F24: is_superuser | G24: boolean | H24: BooleanField (Django) | I24: No | L24: false | N24: Tiene todos los permisos de Django.
A25: usuario | B25: Usuario | C25: Identidad y acceso | D25: Implementado | E25: 11 | F25: last_login | G25: timestamp with time zone | H25: DateTimeField (Django) | I25: Sí | N25: Último inicio de sesión.
A26: usuario | B26: Usuario | C26: Identidad y acceso | D26: Implementado | E26: 12 | F26: fecha_registro | G26: timestamp with time zone | H26: DateTimeField(auto_now_add) | I26: No | L26: Ahora | N26: Fecha de creación de la cuenta.
A27: solicitud_de_acceso | B27: SolicitudDeAcceso | C27: Identidad y acceso | D27: Implementado | E27: 1 | F27: id | G27: bigint | H27: BigAutoField | I27: No | J27: PK | L27: Autoincremental | N27: Identificador interno.
A28: solicitud_de_acceso | B28: SolicitudDeAcceso | C28: Identidad y acceso | D28: Implementado | E28: 2 | F28: negocio | G28: varchar(150) | H28: CharField | I28: No | N28: Nombre del negocio.
A29: solicitud_de_acceso | B29: SolicitudDeAcceso | C29: Identidad y acceso | D29: Implementado | E29: 3 | F29: nombre | G29: varchar(150) | H29: CharField | I29: No | N29: Nombre de contacto.
A30: solicitud_de_acceso | B30: SolicitudDeAcceso | C30: Identidad y acceso | D30: Implementado | E30: 4 | F30: email | G30: varchar(254) | H30: EmailField | I30: No | J30: UQ | M30: Se guarda en minúsculas. | N30: Correo de contacto.
A31: solicitud_de_acceso | B31: SolicitudDeAcceso | C31: Identidad y acceso | D31: Implementado | E31: 5 | F31: telefono | G31: varchar(30) | H31: CharField | I31: No | N31: Teléfono o WhatsApp.
A32: solicitud_de_acceso | B32: SolicitudDeAcceso | C32: Identidad y acceso | D32: Implementado | E32: 6 | F32: mensaje | G32: text | H32: TextField | I32: Sí (vacío) | N32: Qué vende el negocio.
A33: solicitud_de_acceso | B33: SolicitudDeAcceso | C33: Identidad y acceso | D33: Implementado | E33: 7 | F33: estado | G33: varchar(20) | H33: CharField(choices) | I33: No | L33: nueva | M33: nueva | contactada | activada | descartada | N33: Seguimiento de la solicitud.
A34: solicitud_de_acceso | B34: SolicitudDeAcceso | C34: Identidad y acceso | D34: Implementado | E34: 8 | F34: notas | G34: text | H34: TextField | I34: Sí (vacío) | M34: Uso interno. | N34: Notas del administrador de la plataforma.
A35: solicitud_de_acceso | B35: SolicitudDeAcceso | C35: Identidad y acceso | D35: Implementado | E35: 9 | F35: fecha_creacion | G35: timestamp with time zone | H35: DateTimeField(auto_now_add) | I35: No | L35: Ahora | N35: Fecha de la solicitud.
A36: aprobacion_mayorista | B36: AprobacionMayorista | C36: Identidad y acceso | D36: Decisión pendiente | E36: 1 | F36: id | G36: bigint | H36: BigAutoField | I36: No | J36: PK | L36: Autoincremental | N36: Identificador interno.
A37: aprobacion_mayorista | B37: AprobacionMayorista | C37: Identidad y acceso | D37: Decisión pendiente | E37: 2 | F37: tienda_id | G37: bigint | H37: ForeignKey(Tienda) | I37: No | J37: FK | K37: tienda.id · CASCADE | M37: Se toma del token del usuario, nunca del cuerpo de la petición. | N37: Tienda a la que pertenece la fila. Raíz del aislamiento entre tiendas.
A38: aprobacion_mayorista | B38: AprobacionMayorista | C38: Identidad y acceso | D38: Decisión pendiente | E38: 3 | F38: comprador_id | G38: bigint | H38: ForeignKey(Usuario) | I38: No | J38: FK | K38: usuario.id · CASCADE | M38: Debe ser un usuario con rol comprador. | N38: Comprador evaluado.
A39: aprobacion_mayorista | B39: AprobacionMayorista | C39: Identidad y acceso | D39: Decisión pendiente | E39: 4 | F39: estado | G39: varchar(20) | H39: CharField(choices) | I39: No | L39: sin_solicitar | M39: sin_solicitar | pendiente | aprobado | rechazado | N39: Estado de la aprobación.
A40: aprobacion_mayorista | B40: AprobacionMayorista | C40: Identidad y acceso | D40: Decisión pendiente | E40: 5 | F40: fecha_resolucion | G40: timestamp with time zone | H40: DateTimeField | I40: Sí | N40: Cuándo se aprobó o rechazó.
A41: aprobacion_mayorista | B41: AprobacionMayorista | C41: Identidad y acceso | D41: Decisión pendiente | E41: 6 | F41: resuelta_por_id | G41: bigint | H41: ForeignKey(Usuario) | I41: Sí | J41: FK | K41: usuario.id · SET NULL | N41: Usuario de la tienda que resolvió.
A42: aprobacion_mayorista | B42: AprobacionMayorista | C42: Identidad y acceso | D42: Decisión pendiente | E42: 7 | F42: fecha_creacion | G42: timestamp with time zone | H42: DateTimeField(auto_now_add) | I42: No | L42: Ahora | M42: Se guarda en UTC. | N42: Fecha de creación de la fila.
A43: aprobacion_mayorista | B43: AprobacionMayorista | C43: Identidad y acceso | D43: Decisión pendiente | E43: 8 | F43: fecha_edicion | G43: timestamp with time zone | H43: DateTimeField(auto_now) | I43: No | L43: Ahora | M43: Se guarda en UTC. | N43: Fecha de la última modificación.
A44: categoria | B44: Categoria | C44: Catálogo y precios | D44: Planificado | E44: 1 | F44: id | G44: bigint | H44: BigAutoField | I44: No | J44: PK | L44: Autoincremental | N44: Identificador interno.
A45: categoria | B45: Categoria | C45: Catálogo y precios | D45: Planificado | E45: 2 | F45: tienda_id | G45: bigint | H45: ForeignKey(Tienda) | I45: No | J45: FK | K45: tienda.id · CASCADE | M45: Se toma del token del usuario, nunca del cuerpo de la petición. | N45: Tienda a la que pertenece la fila. Raíz del aislamiento entre tiendas.
A46: categoria | B46: Categoria | C46: Catálogo y precios | D46: Planificado | E46: 3 | F46: nombre | G46: varchar(60) | H46: CharField | I46: No | M46: UNIQUE (tienda, nombre). | N46: Ej.: anillos, aros, cadenas, pulseras, colgantes.
A47: categoria | B47: Categoria | C47: Catálogo y precios | D47: Planificado | E47: 4 | F47: fecha_creacion | G47: timestamp with time zone | H47: DateTimeField(auto_now_add) | I47: No | L47: Ahora | M47: Se guarda en UTC. | N47: Fecha de creación de la fila.
A48: categoria | B48: Categoria | C48: Catálogo y precios | D48: Planificado | E48: 5 | F48: fecha_edicion | G48: timestamp with time zone | H48: DateTimeField(auto_now) | I48: No | L48: Ahora | M48: Se guarda en UTC. | N48: Fecha de la última modificación.
A49: lote | B49: Lote | C49: Catálogo y precios | D49: Planificado | E49: 1 | F49: id | G49: bigint | H49: BigAutoField | I49: No | J49: PK | L49: Autoincremental | N49: Identificador interno.
A50: lote | B50: Lote | C50: Catálogo y precios | D50: Planificado | E50: 2 | F50: tienda_id | G50: bigint | H50: ForeignKey(Tienda) | I50: No | J50: FK | K50: tienda.id · CASCADE | M50: Se toma del token del usuario, nunca del cuerpo de la petición. | N50: Tienda a la que pertenece la fila. Raíz del aislamiento entre tiendas.
A51: lote | B51: Lote | C51: Catálogo y precios | D51: Planificado | E51: 3 | F51: codigo | G51: varchar(40) | H51: CharField | I51: No | J51: UQ | M51: UNIQUE (tienda, codigo). Clave de la carga masiva. | N51: Código del lote definido por la tienda.
A52: lote | B52: Lote | C52: Catálogo y precios | D52: Planificado | E52: 4 | F52: nombre | G52: varchar(150) | H52: CharField | I52: No | N52: Nombre visible del lote.
A53: lote | B53: Lote | C53: Catálogo y precios | D53: Planificado | E53: 5 | F53: precio_neto | G53: integer | H53: PositiveIntegerField | I53: No | M53: Pesos chilenos, entero, sin IVA. | N53: Precio del lote.
A54: lote | B54: Lote | C54: Catálogo y precios | D54: Planificado | E54: 6 | F54: tipo_cupo | G54: varchar(10) | H54: CharField(choices) | I54: No | L54: MULTIPLE | M54: MULTIPLE | UNICO | N54: Si el lote se puede volver a vender.
A55: lote | B55: Lote | C55: Catálogo y precios | D55: Planificado | E55: 7 | F55: cupos_totales | G55: integer | H55: PositiveIntegerField | I55: No | L55: 1 | M55: CHECK: si tipo_cupo = UNICO, vale 1. | N55: Cuántas veces se puede vender.
A56: lote | B56: Lote | C56: Catálogo y precios | D56: Planificado | E56: 8 | F56: cupos_disponibles | G56: integer | H56: PositiveIntegerField | I56: No | M56: CHECK: 0 ≤ cupos_disponibles ≤ cupos_totales. Se descuenta con bloqueo de fila al confirmar. | N56: Cupos que quedan.
A57: lote | B57: Lote | C57: Catálogo y precios | D57: Planificado | E57: 9 | F57: cantidad_piezas | G57: integer | H57: PositiveIntegerField | I57: No | M57: Debe igualar la suma de composicion_lote.cantidad. | N57: Total de piezas del lote.
A58: lote | B58: Lote | C58: Catálogo y precios | D58: Planificado | E58: 10 | F58: material | G58: varchar(60) | H58: CharField | I58: No | M58: Ej.: acero, plata, enchape de plata, fantasía. | N58: Material predominante.
A59: lote | B59: Lote | C59: Catálogo y precios | D59: Planificado | E59: 11 | F59: foto | G59: varchar(255) | H59: CharField | I59: Sí (vacío) | M59: Clave del objeto en R2; el nombre lo genera el sistema. | N59: Foto del lote.
A60: lote | B60: Lote | C60: Catálogo y precios | D60: Planificado | E60: 12 | F60: activo | G60: boolean | H60: BooleanField | I60: No | L60: true | M60: La carga masiva nunca borra: desactiva. | N60: Si se muestra en la tienda.
A61: lote | B61: Lote | C61: Catálogo y precios | D61: Planificado | E61: 13 | F61: fecha_creacion | G61: timestamp with time zone | H61: DateTimeField(auto_now_add) | I61: No | L61: Ahora | M61: Se guarda en UTC. | N61: Fecha de creación de la fila.
A62: lote | B62: Lote | C62: Catálogo y precios | D62: Planificado | E62: 14 | F62: fecha_edicion | G62: timestamp with time zone | H62: DateTimeField(auto_now) | I62: No | L62: Ahora | M62: Se guarda en UTC. | N62: Fecha de la última modificación.
A63: composicion_lote | B63: ComposicionLote | C63: Catálogo y precios | D63: Planificado | E63: 1 | F63: id | G63: bigint | H63: BigAutoField | I63: No | J63: PK | L63: Autoincremental | N63: Identificador interno.
A64: composicion_lote | B64: ComposicionLote | C64: Catálogo y precios | D64: Planificado | E64: 2 | F64: tienda_id | G64: bigint | H64: ForeignKey(Tienda) | I64: No | J64: FK | K64: tienda.id · CASCADE | M64: Se toma del token del usuario, nunca del cuerpo de la petición. | N64: Tienda a la que pertenece la fila. Raíz del aislamiento entre tiendas.
A65: composicion_lote | B65: ComposicionLote | C65: Catálogo y precios | D65: Planificado | E65: 3 | F65: lote_id | G65: bigint | H65: ForeignKey(Lote) | I65: No | J65: FK | K65: lote.id · CASCADE | M65: UNIQUE (lote, categoria). | N65: Lote al que pertenece.
A66: composicion_lote | B66: ComposicionLote | C66: Catálogo y precios | D66: Planificado | E66: 4 | F66: categoria_id | G66: bigint | H66: ForeignKey(Categoria) | I66: No | J66: FK | K66: categoria.id · PROTECT | M66: Debe ser de la misma tienda que el lote. | N66: Categoría de las piezas.
A67: composicion_lote | B67: ComposicionLote | C67: Catálogo y precios | D67: Planificado | E67: 5 | F67: cantidad | G67: integer | H67: PositiveIntegerField | I67: No | M67: Mayor que 0. | N67: Piezas de esa categoría.
A68: composicion_lote | B68: ComposicionLote | C68: Catálogo y precios | D68: Planificado | E68: 6 | F68: fecha_creacion | G68: timestamp with time zone | H68: DateTimeField(auto_now_add) | I68: No | L68: Ahora | M68: Se guarda en UTC. | N68: Fecha de creación de la fila.
A69: composicion_lote | B69: ComposicionLote | C69: Catálogo y precios | D69: Planificado | E69: 7 | F69: fecha_edicion | G69: timestamp with time zone | H69: DateTimeField(auto_now) | I69: No | L69: Ahora | M69: Se guarda en UTC. | N69: Fecha de la última modificación.
A70: linea_granel | B70: LineaGranel | C70: Catálogo y precios | D70: Planificado | E70: 1 | F70: id | G70: bigint | H70: BigAutoField | I70: No | J70: PK | L70: Autoincremental | N70: Identificador interno.
A71: linea_granel | B71: LineaGranel | C71: Catálogo y precios | D71: Planificado | E71: 2 | F71: tienda_id | G71: bigint | H71: ForeignKey(Tienda) | I71: No | J71: FK | K71: tienda.id · CASCADE | M71: Se toma del token del usuario, nunca del cuerpo de la petición. | N71: Tienda a la que pertenece la fila. Raíz del aislamiento entre tiendas.
A72: linea_granel | B72: LineaGranel | C72: Catálogo y precios | D72: Planificado | E72: 3 | F72: codigo | G72: varchar(40) | H72: CharField | I72: No | J72: UQ | M72: UNIQUE (tienda, codigo). | N72: Código de la línea.
A73: linea_granel | B73: LineaGranel | C73: Catálogo y precios | D73: Planificado | E73: 4 | F73: nombre | G73: varchar(150) | H73: CharField | I73: No | N73: Ej.: Gramo de hombre.
A74: linea_granel | B74: LineaGranel | C74: Catálogo y precios | D74: Planificado | E74: 5 | F74: material | G74: varchar(60) | H74: CharField | I74: No | N74: Ej.: enchape de plata, plata colombiana.
A75: linea_granel | B75: LineaGranel | C75: Catálogo y precios | D75: Planificado | E75: 6 | F75: categorias | G75: varchar(200) | H75: CharField | I75: Sí (vacío) | M75: Texto descriptivo. | N75: Ej.: cadenas, pulseras.
A76: linea_granel | B76: LineaGranel | C76: Catálogo y precios | D76: Planificado | E76: 7 | F76: disponible | G76: boolean | H76: BooleanField | I76: No | L76: true | N76: Si se puede comprar.
A77: linea_granel | B77: LineaGranel | C77: Catálogo y precios | D77: Planificado | E77: 8 | F77: foto | G77: varchar(255) | H77: CharField | I77: Sí (vacío) | M77: Clave del objeto en R2. | N77: Foto de referencia.
A78: linea_granel | B78: LineaGranel | C78: Catálogo y precios | D78: Planificado | E78: 9 | F78: fecha_creacion | G78: timestamp with time zone | H78: DateTimeField(auto_now_add) | I78: No | L78: Ahora | M78: Se guarda en UTC. | N78: Fecha de creación de la fila.
A79: linea_granel | B79: LineaGranel | C79: Catálogo y precios | D79: Planificado | E79: 10 | F79: fecha_edicion | G79: timestamp with time zone | H79: DateTimeField(auto_now) | I79: No | L79: Ahora | M79: Se guarda en UTC. | N79: Fecha de la última modificación.
A80: tramo_precio | B80: TramoPrecio | C80: Catálogo y precios | D80: Planificado | E80: 1 | F80: id | G80: bigint | H80: BigAutoField | I80: No | J80: PK | L80: Autoincremental | N80: Identificador interno.
A81: tramo_precio | B81: TramoPrecio | C81: Catálogo y precios | D81: Planificado | E81: 2 | F81: tienda_id | G81: bigint | H81: ForeignKey(Tienda) | I81: No | J81: FK | K81: tienda.id · CASCADE | M81: Se toma del token del usuario, nunca del cuerpo de la petición. | N81: Tienda a la que pertenece la fila. Raíz del aislamiento entre tiendas.
A82: tramo_precio | B82: TramoPrecio | C82: Catálogo y precios | D82: Planificado | E82: 3 | F82: linea_granel_id | G82: bigint | H82: ForeignKey(LineaGranel) | I82: Sí | J82: FK | K82: linea_granel.id · CASCADE | M82: Nulo = tramo de descuento por cantidad de lotes. | N82: Línea a la que aplica.
A83: tramo_precio | B83: TramoPrecio | C83: Catálogo y precios | D83: Planificado | E83: 4 | F83: unidad_umbral | G83: varchar(10) | H83: CharField(choices) | I83: No | M83: pesos | gramos | lotes | N83: En qué se mide el umbral.
A84: tramo_precio | B84: TramoPrecio | C84: Catálogo y precios | D84: Planificado | E84: 5 | F84: umbral | G84: numeric(12,2) | H84: DecimalField | I84: No | M84: Inclusivo (>=). UNIQUE (linea, unidad, umbral). | N84: Desde qué cantidad aplica.
A85: tramo_precio | B85: TramoPrecio | C85: Catálogo y precios | D85: Planificado | E85: 6 | F85: valor | G85: integer | H85: PositiveIntegerField | I85: No | M85: Granel: precio por gramo neto. Lotes: % de descuento. | N85: Precio o descuento del tramo.
A86: tramo_precio | B86: TramoPrecio | C86: Catálogo y precios | D86: Planificado | E86: 7 | F86: fecha_creacion | G86: timestamp with time zone | H86: DateTimeField(auto_now_add) | I86: No | L86: Ahora | M86: Se guarda en UTC. | N86: Fecha de creación de la fila.
A87: tramo_precio | B87: TramoPrecio | C87: Catálogo y precios | D87: Planificado | E87: 8 | F87: fecha_edicion | G87: timestamp with time zone | H87: DateTimeField(auto_now) | I87: No | L87: Ahora | M87: Se guarda en UTC. | N87: Fecha de la última modificación.
A88: pedido | B88: Pedido | C88: Pedidos | D88: Planificado | E88: 1 | F88: id | G88: bigint | H88: BigAutoField | I88: No | J88: PK | L88: Autoincremental | N88: Identificador interno.
A89: pedido | B89: Pedido | C89: Pedidos | D89: Planificado | E89: 2 | F89: tienda_id | G89: bigint | H89: ForeignKey(Tienda) | I89: No | J89: FK | K89: tienda.id · CASCADE | M89: Se toma del token del usuario, nunca del cuerpo de la petición. | N89: Tienda a la que pertenece la fila. Raíz del aislamiento entre tiendas.
A90: pedido | B90: Pedido | C90: Pedidos | D90: Planificado | E90: 3 | F90: comprador_id | G90: bigint | H90: ForeignKey(Usuario) | I90: No | J90: FK | K90: usuario.id · PROTECT | M90: Rol comprador. | N90: Quién hizo el pedido.
A91: pedido | B91: Pedido | C91: Pedidos | D91: Planificado | E91: 4 | F91: numero | G91: integer | H91: PositiveIntegerField | I91: No | J91: UQ | M91: UNIQUE (tienda, numero). | N91: Número correlativo visible.
A92: pedido | B92: Pedido | C92: Pedidos | D92: Planificado | E92: 5 | F92: estado | G92: varchar(20) | H92: CharField(choices) | I92: No | L92: borrador | M92: borrador → confirmado → preparacion → entregado; anulado desde cualquiera menos entregado. | N92: Estado del pedido.
A93: pedido | B93: Pedido | C93: Pedidos | D93: Planificado | E93: 6 | F93: neto | G93: integer | H93: PositiveIntegerField | I93: No | L93: 0 | M93: Lo recalcula el backend; nunca se usa el del navegador. | N93: Suma de los netos de las líneas.
A94: pedido | B94: Pedido | C94: Pedidos | D94: Planificado | E94: 7 | F94: iva | G94: integer | H94: PositiveIntegerField | I94: No | L94: 0 | M94: 19%, redondeo medio hacia arriba con Decimal. | N94: IVA del pedido.
A95: pedido | B95: Pedido | C95: Pedidos | D95: Planificado | E95: 8 | F95: total | G95: integer | H95: PositiveIntegerField | I95: No | L95: 0 | M95: neto + iva. | N95: Total del pedido.
A96: pedido | B96: Pedido | C96: Pedidos | D96: Planificado | E96: 9 | F96: confirmado_en | G96: timestamp with time zone | H96: DateTimeField | I96: Sí | N96: Cuándo se confirmó.
A97: pedido | B97: Pedido | C97: Pedidos | D97: Planificado | E97: 10 | F97: vence_en | G97: timestamp with time zone | H97: DateTimeField | I97: Sí | M97: Plazo pendiente de definir con el cliente. | N97: Si no se paga antes, se liberan los cupos.
A98: pedido | B98: Pedido | C98: Pedidos | D98: Planificado | E98: 11 | F98: fecha_creacion | G98: timestamp with time zone | H98: DateTimeField(auto_now_add) | I98: No | L98: Ahora | M98: Se guarda en UTC. | N98: Fecha de creación de la fila.
A99: pedido | B99: Pedido | C99: Pedidos | D99: Planificado | E99: 12 | F99: fecha_edicion | G99: timestamp with time zone | H99: DateTimeField(auto_now) | I99: No | L99: Ahora | M99: Se guarda en UTC. | N99: Fecha de la última modificación.
A100: linea_pedido | B100: LineaPedido | C100: Pedidos | D100: Planificado | E100: 1 | F100: id | G100: bigint | H100: BigAutoField | I100: No | J100: PK | L100: Autoincremental | N100: Identificador interno.
...

Sheet Restricciones
A1: Tabla | B1: Tipo | C1: Definición | D1: Para qué sirve | E1: Estado
A2: usuario | B2: CHECK | C2: rol ∈ (dueno_tienda, vendedor) ⇒ tienda_id no nulo; rol ∈ (admin_plataforma, comprador) ⇒ tienda_id nulo | D2: Que nadie trabaje en una tienda sin pertenecer a ella, ni un comprador quede atado a una. | E2: Implementado
A3: aprobacion_mayorista | B3: UNIQUE | C3: (tienda_id, comprador_id) | D3: Un estado por comprador en cada tienda. | E3: Decisión pendiente
A4: categoria | B4: UNIQUE | C4: (tienda_id, nombre) | D4: Sin categorías repetidas en una tienda. | E4: Planificado
A5: lote | B5: UNIQUE | C5: (tienda_id, codigo) | D5: Que la carga masiva actualice en vez de duplicar. | E5: Planificado
A6: lote | B6: CHECK | C6: 0 ≤ cupos_disponibles ≤ cupos_totales | D6: Nunca vender más cupos de los que existen. | E6: Planificado
A7: lote | B7: CHECK | C7: tipo_cupo = UNICO ⇒ cupos_totales = 1 | D7: Un cupo único se vende una sola vez. | E7: Planificado
A8: lote | B8: VALIDACIÓN | C8: cantidad_piezas = suma de composicion_lote.cantidad | D8: La composición cuadra con el total de piezas (se valida al guardar). | E8: Planificado
A9: composicion_lote | B9: UNIQUE | C9: (lote_id, categoria_id) | D9: Una fila por categoría en cada lote. | E9: Planificado
A10: linea_granel | B10: UNIQUE | C10: (tienda_id, codigo) | D10: Que la carga masiva actualice en vez de duplicar. | E10: Planificado
A11: tramo_precio | B11: UNIQUE | C11: (linea_granel_id, unidad_umbral, umbral) | D11: Sin tramos repetidos en una misma lista. | E11: Planificado
A12: pedido | B12: UNIQUE | C12: (tienda_id, numero) | D12: Número de pedido correlativo por tienda. | E12: Planificado
... A19: visita | B19: UNIQUE | C19: (tienda_id, inicio, posicion) | D19: Dos compradores no pueden tomar el mismo lugar en el mismo horario. | E19: Congelado
